
{"comments": [{"text": "#hastag1 #hastag2 @amigo1 @amigo2 @amigo3", "pk": 17869008076205413, "created_at_utc": 1519799961, "user_id": 1519549189, "status": "Active", "did_report_as_spam": "False", "user": {"full_name": "Andrea Lacruz Villareal", "pk": 1519549189, "username": "andrelacruz", "is_verified": "False", "profile_pic_id": "1709188385132096919_1519549189", "profile_pic_url": "https://scontent-mia3-2.cdninstagram.com/vp/9785289f92445738c20ab30bbf3310b2/5B4CAC58/t51.2885-19/s150x150/27575238_171584776793370_1302436243962855424_n.jpg", "is_private": "False"}, "comment_like_count": 0, "has_liked_comment": "False", "bit_flags": 0, "inline_composer_display_condition": "never", "content_type": "comment", "created_at": 1519799961, "type": 0}, {"text": "#hastag1 #hastag2 @amigo1 @amigo2", "pk": 17914464832110653, "created_at_utc": 1519821030, "user_id": 490792820, "status": "Active", "did_report_as_spam": "False", "user": {"full_name": "Yeniree Cardenas", "pk": 490792820, "username": "yenig28", "is_verified": "False", "profile_pic_id": "1315926384555758996_490792820", "profile_pic_url": "https://scontent-mia3-2.cdninstagram.com/vp/51ef1358f6a0372e7ff98437ddca408e/5B365D34/t51.2885-19/s150x150/13636022_593212280847280_181011587_a.jpg", "is_private": "True"}, "comment_like_count": 0, "has_liked_comment": "False", "bit_flags": 0, "inline_composer_display_condition": "never", "content_type": "comment", "created_at": 1519821030, "type": 0}, {"text": "#hastag1 #hastag2", "pk": 17868803866206501, "created_at_utc": 1519821322, "user_id": 611900053, "status": "Active", "did_report_as_spam": "False", "user": {"full_name": "Eleazar Araujo Torres", "pk": 611900053, "username": "earaujo17", "is_verified": "False", "profile_pic_id": "1550206126993124521_611900053", "profile_pic_url": "https://scontent-mia3-2.cdninstagram.com/vp/c871b1c6194ad63c3949969184177ee3/5B43F076/t51.2885-19/s150x150/19624122_436289903424042_2039911544917065728_a.jpg", "is_private": "False"}, "comment_like_count": 0, "has_liked_comment": "False", "bit_flags": 0, "inline_composer_display_condition": "never", "content_type": "comment", "created_at": 1519821322, "type": 0}, {"text": "Vamos a ganar #hastag1 #hastag2 #hastag3 @andrelacruz @yenig28 @earaujo17", "pk": 17919049210079362, "created_at_utc": 1519822737, "user_id": 299520449, "status": "Active", "did_report_as_spam": "False", "user": {"full_name": "Manuel Araujo", "pk": 299520449, "username": "manuel_araujo10", "is_verified": "False", "profile_pic_id": "1663287004094021113_299520449", "profile_pic_url": "https://scontent-mia3-2.cdninstagram.com/vp/335a51ddc83f44912e5f3020330de5d5/5B14EC40/t51.2885-19/s150x150/24327145_867481223425465_5949746640993648640_n.jpg", "is_private": "False"}, "comment_like_count": 0, "has_liked_comment": "False", "bit_flags": 0, "inline_composer_display_condition": "never", "content_type": "comment", "created_at": 1519822737, "type": 0}], "has_more_headload_comments": "False", "media_header_display": "none", "preview_comments": [], "comment_count": 4, "status": "ok", "caption_is_edited": "False", "has_more_comments": "False", "comment_likes_enabled": "True", "caption": {"text": "Encabezado de la pagina\n- Debes seguirnos\n- Debes darle like a esta foto\n- Debes usar los hastags: #hastag1 #hastag2\n- Debes seguir estas cuentas: @cuenta1 @cuenta2\n- Etiquetar a 3 amigos\n- Tus amigos etiquetados deben hacer like a esta publicación\n- Tus amigos etiquetados deben seguir a nuestra cuenta\n- Tus amigos etiquetados deben seguir a las cuentas nombradas\npie de la pagina", "pk": 17927587420005102, "created_at_utc": 1519799610, "user_id": 7053015697, "status": "Active", "did_report_as_spam": "False", "user": {"full_name": "Manuel Araujo", "pk": 7053015697, "username": "maraujo1511", "is_verified": "False", "profile_pic_id": "1707713113870352040_7053015697", "profile_pic_url": "https://scontent-mia3-2.cdninstagram.com/vp/7f1d2696f3a05b684bad1f416498f0c4/5B15A7D7/t51.2885-19/s150x150/26871281_1827501704209838_7635371805452009472_n.jpg", "is_private": "False"}, "has_translation": "True", "bit_flags": 0, "content_type": "comment", "created_at": 1519799610, "type": 1}}
